tree_sitter_streamdevice_proto/__init__.py
tree_sitter_streamdevice_proto/__init__.pyi
tree_sitter_streamdevice_proto/_binding.abi3.so
tree_sitter_streamdevice_proto/binding.c
tree_sitter_streamdevice_proto/py.typed
tree_sitter_streamdevice_proto/queries/highlights.scm
tree_sitter_streamdevice_proto/queries/injections.scm
tree_sitter_streamdevice_proto-0.2.1.dist-info/METADATA
tree_sitter_streamdevice_proto-0.2.1.dist-info/WHEEL
tree_sitter_streamdevice_proto-0.2.1.dist-info/top_level.txt
tree_sitter_streamdevice_proto-0.2.1.dist-info/RECORD
tree_sitter_streamdevice_proto-0.2.1.dist-info/licenses/LICENSE
