Metadata-Version: 2.4
Name: tree-sitter-streamdevice-proto
Version: 0.2.1
Summary: tree-sitter grammar for StreamDevice's .proto files
Author-email: Rémi NICOLE <remi.nicole@cea.fr>
License: MIT
Project-URL: Homepage, https://github.com/minijackson/tree-sitter-streamdevice-proto
Keywords: incremental,parsing,tree-sitter,epics,streamdevice
Classifier: Intended Audience :: Developers
Classifier: Topic :: Software Development :: Compilers
Classifier: Topic :: Text Processing :: Linguistic
Classifier: Typing :: Typed
Requires-Python: >=3.10
License-File: LICENSE
Provides-Extra: core
Requires-Dist: tree-sitter~=0.24; extra == "core"
Dynamic: license-file
